uber_central_mcp/__init__.py
uber_central_mcp/__main__.py
uber_central_mcp/server.py
uber_central_mcp-1.1.0.dist-info/METADATA
uber_central_mcp-1.1.0.dist-info/WHEEL
uber_central_mcp-1.1.0.dist-info/entry_points.txt
uber_central_mcp-1.1.0.dist-info/licenses/LICENSE
uber_central_mcp-1.1.0.dist-info/RECORD
