Metadata-Version: 2.4
Name: uber-central-mcp
Version: 1.1.0
Summary: Model Context Protocol (MCP) server for Uber Central API integration
Project-URL: Homepage, https://github.com/uber-central/uber-central-mcp
Project-URL: Repository, https://github.com/uber-central/uber-central-mcp
Project-URL: Issues, https://github.com/uber-central/uber-central-mcp/issues
Author: Uber Central Team
License: MIT License
License-File: LICENSE
Keywords: fastmcp,mcp,model-context-protocol,ride-booking,uber
Classifier: Development Status :: 4 - Beta
Classifier: Intended Audience :: Developers
Classifier: License :: OSI Approved :: MIT License
Classifier: Programming Language :: Python :: 3
Classifier: Programming Language :: Python :: 3.10
Classifier: Programming Language :: Python :: 3.11
Classifier: Programming Language :: Python :: 3.12
Classifier: Topic :: Communications
Classifier: Topic :: Internet :: WWW/HTTP :: HTTP Servers
Classifier: Topic :: Software Development :: Libraries :: Python Modules
Requires-Python: >=3.10
Requires-Dist: httpx>=0.28.1
Requires-Dist: mcp[cli]>=1.12.3
Requires-Dist: pydantic>=2.11.7
